aisteel/__init__.py
aisteel/_modidx.py
aisteel/core.py
aisteel-0.0.1.dist-info/LICENSE
aisteel-0.0.1.dist-info/METADATA
aisteel-0.0.1.dist-info/WHEEL
aisteel-0.0.1.dist-info/entry_points.txt
aisteel-0.0.1.dist-info/top_level.txt
aisteel-0.0.1.dist-info/RECORD
