Metadata-Version: 2.1
Name: aisteel
Version: 0.0.1
Summary: Python library using LLMs to create FEM models for steel structures, leveraging Metku for calculations. Aimed at students and structural engineers, it streamlines the design process according to Eurocode standards, emphasizing ease of use.
Home-page: https://github.com/BWINB/aisteel
Author: BWINB
Author-email: bjorn.winberg@live.com
License: Apache Software License 2.0
Keywords: nbdev jupyter notebook python
Classifier: Development Status :: 4 - Beta
Classifier: Intended Audience :: Developers
Classifier: Natural Language :: English
Classifier: Programming Language :: Python :: 3.7
Classifier: Programming Language :: Python :: 3.8
Classifier: Programming Language :: Python :: 3.9
Classifier: Programming Language :: Python :: 3.10
Classifier: Programming Language :: Python :: 3.11
Classifier: Programming Language :: Python :: 3.12
Classifier: License :: OSI Approved :: Apache Software License
Requires-Python: >=3.7
License-File: LICENSE
Provides-Extra: dev
